voxtream/__init__.py
voxtream/app.py
voxtream/benchmark.py
voxtream/dataset.py
voxtream/generator.py
voxtream/model.py
voxtream/run.py
voxtream/train.py
voxtream/trainer.py
voxtream/utils/__init__.py
voxtream/utils/aligner.py
voxtream/utils/generator.py
voxtream/utils/model.py
voxtream/utils/sampling.py
voxtream/utils/trainer.py
voxtream-0.1.4.dist-info/METADATA
voxtream-0.1.4.dist-info/WHEEL
voxtream-0.1.4.dist-info/entry_points.txt
voxtream-0.1.4.dist-info/top_level.txt
voxtream-0.1.4.dist-info/RECORD
