Metadata-Version: 2.4
Name: voxtream
Version: 0.1.4
Summary: Full-Stream Zero-shot TTS model with Extremely Low Latency
Author-email: Nikita Torgashov <torgaschov.nikita@gmail.com>
License: MIT
Project-URL: Homepage, https://herimor.github.io/voxtream
Project-URL: Bug Reports, https://github.com/herimor/voxtream/issues
Project-URL: Source, https://github.com/herimor/voxtream
Keywords: text-to-speech,streaming,tts,speech-synthesis,voice-cloning
Classifier: Development Status :: 3 - Alpha
Classifier: Intended Audience :: Developers
Classifier: Topic :: Multimedia :: Sound/Audio
Classifier: License :: OSI Approved :: MIT License
Classifier: Programming Language :: Python :: 3
Requires-Python: >=3.9
Requires-Dist: torch==2.4.0
Requires-Dist: torchaudio==2.4.0
Requires-Dist: torchtune==0.4.0
Requires-Dist: torchao==0.9.0
Requires-Dist: moshi==0.2.2
Requires-Dist: transformers==4.50.0
Requires-Dist: huggingface_hub==0.28.1
Requires-Dist: g2p-en==2.1.0
Requires-Dist: librosa==0.11.0
Requires-Dist: soundfile==0.13.1
Requires-Dist: inflect==7.5.0
Requires-Dist: nltk==3.9.1
Requires-Dist: gradio==4.44.1
Requires-Dist: gradio_client==1.3.0
Requires-Dist: pydantic==2.10.6
Provides-Extra: dev
Requires-Dist: black; extra == "dev"
Requires-Dist: isort; extra == "dev"
Requires-Dist: flake8; extra == "dev"
Requires-Dist: mypy; extra == "dev"
Requires-Dist: pytest; extra == "dev"
